thoth/build_analysers/__about__.py
thoth/build_analysers/__init__.py
thoth/build_analysers/analysis.py
thoth/build_analysers/preprocessing.py
thoth/build_analysers/parsing/__init__.py
thoth/build_analysers/parsing/handlers/__init__.py
thoth/build_analysers/parsing/handlers/base.py
thoth/build_analysers/parsing/handlers/dnf.py
thoth/build_analysers/parsing/handlers/pip.py
thoth/build_analysers/parsing/handlers/pip3.py
thoth/build_analysers/parsing/handlers/pipenv.py
thoth/build_analysers/parsing/handlers/yum.py
thoth/build_analysers/resources/patterns.pip.csv
thoth/build_analysers/resources/patterns.pipenv.csv
thoth_build_analysers-0.1.0.dist-info/LICENSE
thoth_build_analysers-0.1.0.dist-info/METADATA
thoth_build_analysers-0.1.0.dist-info/WHEEL
thoth_build_analysers-0.1.0.dist-info/top_level.txt
thoth_build_analysers-0.1.0.dist-info/RECORD
